setup.py
ooxx1024/__init__.py
ooxx1024/core.py
ooxx1024.egg-info/PKG-INFO
ooxx1024.egg-info/SOURCES.txt
ooxx1024.egg-info/dependency_links.txt
ooxx1024.egg-info/not-zip-safe
ooxx1024.egg-info/requires.txt
ooxx1024.egg-info/top_level.txt