Metadata-Version: 1.0
Name: ooxx1024
Version: 0.1.0
Summary: A high-speed Robust Torrent Download Package
Home-page: UNKNOWN
Author: Rokic
Author-email: UNKNOWN
License: UNKNOWN
Platform: UNKNOWN
